<?xml version="1.0" encoding="utf-8"?>
<animNode x_extends="default.xml">
	<m_Name>PZH_walk2</m_Name>
	<m_AnimName>Zombie_Walk4</m_AnimName>
	<m_SpeedScale>0.60</m_SpeedScale>
	<m_Conditions />
	<m_Conditions>
		<m_Name>zombieWalkType</m_Name>
		<m_Type>STRING</m_Type>
		<m_StringValue>PZH_walk2</m_StringValue>
	</m_Conditions>
	<m_Events>
		<m_EventName>Footstep</m_EventName>
		<m_TimePc>0.15</m_TimePc>
		<m_ParameterValue>walk</m_ParameterValue>
	</m_Events>
	<m_Events>
		<m_EventName>Footstep</m_EventName>
		<m_TimePc>0.6</m_TimePc>
		<m_ParameterValue>walk</m_ParameterValue>
	</m_Events>
</animNode>